django_detailed_request_logging/__init__.py
django_detailed_request_logging/middleware.py
django_detailed_request_logging-1.2.0.dist-info/LICENSE
django_detailed_request_logging-1.2.0.dist-info/METADATA
django_detailed_request_logging-1.2.0.dist-info/WHEEL
django_detailed_request_logging-1.2.0.dist-info/top_level.txt
django_detailed_request_logging-1.2.0.dist-info/RECORD
