Metadata-Version: 2.1
Name: django-detailed-request-logging
Version: 1.2.0
Summary: Middleware to log requests in Django with more detailed information.
Home-page: https://gitlab.com/biomedit/django-detailed-request-logging
Author: Jaroslaw Surkont, Gerhard Bräunlich, Robin Engler, Christian Ribeaud, François Martin
Author-email: jaroslaw.surkont@unibas.ch, gerhard.braeunlich@id.ethz.ch, robin.engler@sib.swiss, christian.ribeaud@karakun.com, francois.martin@karakun.com
License: LGPL3
Platform: UNKNOWN
Classifier: Programming Language :: Python :: 3
Classifier: Programming Language :: Python :: 3.7
Classifier: Programming Language :: Python :: 3.8
Classifier: Programming Language :: Python :: 3.9
Classifier: License :: OSI Approved :: GNU Lesser General Public License v3 (LGPLv3)
Classifier: Operating System :: OS Independent
Requires-Python: >=3.7
License-File: LICENSE
Requires-Dist: Django (>=3.2)
Requires-Dist: djangorestframework (>=3.12)
Provides-Extra: stubs
Requires-Dist: django-stubs ; extra == 'stubs'
Requires-Dist: djangorestframework-stubs ; extra == 'stubs'
Provides-Extra: test
Requires-Dist: assertpy ; extra == 'test'
Requires-Dist: pytest ; extra == 'test'
Requires-Dist: pytest-django ; extra == 'test'
